[{"Balthali":" 7","Bhugdeu_Mahankalchaur":"12","Chalalganeshsthan":"17","Chyamrangbesi":" 6","Chyasingkharka":"17","other":" 5","_row":"Adibasi Janjati"},{"Balthali":" 4","Bhugdeu_Mahankalchaur":" 2","Chalalganeshsthan":" 0","Chyamrangbesi":"12","Chyasingkharka":" 0","other":"11","_row":"Brahmin"},{"Balthali":"6","Bhugdeu_Mahankalchaur":"3","Chalalganeshsthan":"1","Chyamrangbesi":"0","Chyasingkharka":"1","other":"0","_row":"Chhetri"},{"Balthali":"1","Bhugdeu_Mahankalchaur":"1","Chalalganeshsthan":"0","Chyamrangbesi":"0","Chyasingkharka":"0","other":"1","_row":"Dalit"},{"Balthali":"0","Bhugdeu_Mahankalchaur":"0","Chalalganeshsthan":"0","Chyamrangbesi":"0","Chyasingkharka":"0","other":"0","_row":"Madhesi"},{"Balthali":"0","Bhugdeu_Mahankalchaur":"0","Chalalganeshsthan":"0","Chyamrangbesi":"0","Chyasingkharka":"0","other":"0","_row":"Other"},{"Balthali":"10","Bhugdeu_Mahankalchaur":"14","Chalalganeshsthan":"12","Chyamrangbesi":"11","Chyasingkharka":"12","other":"14","_row":"Household Without Disablity"},{"Balthali":"8","Bhugdeu_Mahankalchaur":"4","Chalalganeshsthan":"6","Chyamrangbesi":"7","Chyasingkharka":"6","other":"3","_row":"Household With Disablity"},{"Balthali":"12","Bhugdeu_Mahankalchaur":"13","Chalalganeshsthan":" 8","Chyamrangbesi":"12","Chyasingkharka":"12","other":"11","_row":"No Debt Due to Earthquake"},{"Balthali":" 6","Bhugdeu_Mahankalchaur":" 5","Chalalganeshsthan":"10","Chyamrangbesi":" 6","Chyasingkharka":" 6","other":" 6","_row":"Debt Taken Due to Earthquake"},{"Balthali":"0","Bhugdeu_Mahankalchaur":"0","Chalalganeshsthan":"0","Chyamrangbesi":"1","Chyasingkharka":"1","other":"0","_row":"Did not Recieve Solar Lamp"},{"Balthali":"18","Bhugdeu_Mahankalchaur":"18","Chalalganeshsthan":"18","Chyamrangbesi":"17","Chyasingkharka":"17","other":"17","_row":"Recived Solar Lamp"},{"Balthali":"10","Bhugdeu_Mahankalchaur":"13","Chalalganeshsthan":"13","Chyamrangbesi":"14","Chyasingkharka":"13","other":"13","_row":"Solar Lamp Used Daily"},{"Balthali":"8","Bhugdeu_Mahankalchaur":"3","Chalalganeshsthan":"3","Chyamrangbesi":"2","Chyasingkharka":"2","other":"4","_row":"Solar Lamp Used 4-5 Times/Week"},{"Balthali":"0","Bhugdeu_Mahankalchaur":"1","Chalalganeshsthan":"1","Chyamrangbesi":"1","Chyasingkharka":"1","other":"0","_row":"Solar Lamp Used 2-3 Times/Week"},{"Balthali":"0","Bhugdeu_Mahankalchaur":"1","Chalalganeshsthan":"0","Chyamrangbesi":"0","Chyasingkharka":"0","other":"0","_row":"Solar Lamp Seldom Used"},{"Balthali":"0","Bhugdeu_Mahankalchaur":"0","Chalalganeshsthan":"1","Chyamrangbesi":"0","Chyasingkharka":"1","other":"0","_row":"Never Used Solar Lamp"},{"Balthali":"8","Bhugdeu_Mahankalchaur":"6","Chalalganeshsthan":"9","Chyamrangbesi":"4","Chyasingkharka":"7","other":"9","_row":"Solar Lamp Enchance Securty: Strongly Agree"},{"Balthali":"10","Bhugdeu_Mahankalchaur":"12","Chalalganeshsthan":" 8","Chyamrangbesi":"12","Chyasingkharka":" 8","other":" 8","_row":"Solar Lamp Enchance Securty: Agree"},{"Balthali":"0","Bhugdeu_Mahankalchaur":"0","Chalalganeshsthan":"0","Chyamrangbesi":"1","Chyasingkharka":"1","other":"0","_row":"Solar Lamp Enchance Securty: Neutral"},{"Balthali":"7","Bhugdeu_Mahankalchaur":"5","Chalalganeshsthan":"8","Chyamrangbesi":"3","Chyasingkharka":"7","other":"4","_row":"Solar Lamp Helps Children Study: Strongly Agree"},{"Balthali":" 9","Bhugdeu_Mahankalchaur":"11","Chalalganeshsthan":" 8","Chyamrangbesi":"10","Chyasingkharka":" 5","other":" 7","_row":"Solar Lamp Helps Children Study: Agree"},{"Balthali":"0","Bhugdeu_Mahankalchaur":"0","Chalalganeshsthan":"0","Chyamrangbesi":"1","Chyasingkharka":"0","other":"0","_row":"Solar Lamp Helps Children Study: Neutral"},{"Balthali":"2","Bhugdeu_Mahankalchaur":"2","Chalalganeshsthan":"1","Chyamrangbesi":"2","Chyasingkharka":"1","other":"3","_row":"Solar Lamp Helps Children Study: No Children"},{"Balthali":"0","Bhugdeu_Mahankalchaur":"0","Chalalganeshsthan":"0","Chyamrangbesi":"1","Chyasingkharka":"3","other":"3","_row":"Solar Lamp Helps Children Study: Children Not in School "},{"Balthali":"6","Bhugdeu_Mahankalchaur":"7","Chalalganeshsthan":"4","Chyamrangbesi":"5","Chyasingkharka":"9","other":"7","_row":"Solar Lamp Saves Money: Strongly Agree"},{"Balthali":"10","Bhugdeu_Mahankalchaur":"10","Chalalganeshsthan":"10","Chyamrangbesi":"11","Chyasingkharka":" 6","other":" 8","_row":"Solar Lamp Saves Money: Agree"},{"Balthali":"2","Bhugdeu_Mahankalchaur":"1","Chalalganeshsthan":"3","Chyamrangbesi":"1","Chyasingkharka":"1","other":"2","_row":"Solar Lamp Saves Money: Neutral"},{"Balthali":"17","Bhugdeu_Mahankalchaur":"17","Chalalganeshsthan":"17","Chyamrangbesi":"17","Chyasingkharka":"15","other":"17","_row":"Did not Require Additional Urgent Items"},{"Balthali":"1","Bhugdeu_Mahankalchaur":"1","Chalalganeshsthan":"1","Chyamrangbesi":"1","Chyasingkharka":"3","other":"0","_row":"Nedded Additional Urgent Items not Present in the Kit"},{"Balthali":" 5000","Bhugdeu_Mahankalchaur":" 7000","Chalalganeshsthan":"20000","Chyamrangbesi":"    0","Chyasingkharka":"50000","other":"    0","_row":"FoodSpending"},{"Balthali":"   0","Bhugdeu_Mahankalchaur":"   0","Chalalganeshsthan":"1350","Chyamrangbesi":"   0","Chyasingkharka":"   0","other":"   0","_row":"HouseholdItemSpending"},{"Balthali":" 80500","Bhugdeu_Mahankalchaur":" 47000","Chalalganeshsthan":"232000","Chyamrangbesi":" 96000","Chyasingkharka":"140000","other":" 78000","_row":"ConstructionSpending"},{"Balthali":"    0","Bhugdeu_Mahankalchaur":"    0","Chalalganeshsthan":"72400","Chyamrangbesi":" 1200","Chyasingkharka":"    0","other":"60000","_row":"SavingAfterDebtSpending"},{"Balthali":" 9","Bhugdeu_Mahankalchaur":"14","Chalalganeshsthan":" 7","Chyamrangbesi":"15","Chyasingkharka":" 9","other":"13","_row":"Respondent Male"},{"Balthali":" 9","Bhugdeu_Mahankalchaur":" 4","Chalalganeshsthan":"11","Chyamrangbesi":" 3","Chyasingkharka":" 9","other":" 4","_row":"Respondent Female"},{"Balthali":"13","Bhugdeu_Mahankalchaur":" 9","Chalalganeshsthan":"16","Chyamrangbesi":" 6","Chyasingkharka":"12","other":" 9","_row":"No Elderly"},{"Balthali":" 5","Bhugdeu_Mahankalchaur":" 9","Chalalganeshsthan":" 2","Chyamrangbesi":"12","Chyasingkharka":" 6","other":" 8","_row":"Has Elderly"},{"Balthali":"17","Bhugdeu_Mahankalchaur":"13","Chalalganeshsthan":"16","Chyamrangbesi":"14","Chyasingkharka":"16","other":"11","_row":"No Preagnant Women"},{"Balthali":"1","Bhugdeu_Mahankalchaur":"5","Chalalganeshsthan":"2","Chyamrangbesi":"4","Chyasingkharka":"2","other":"6","_row":"Has Pregnant Women"},{"Balthali":"18","Bhugdeu_Mahankalchaur":"18","Chalalganeshsthan":"18","Chyamrangbesi":"18","Chyasingkharka":"18","other":"17","_row":"TotalRecords"}]
